magpie/__init__.py
magpie/client.py
magpie/exceptions.py
magpie/models.py
magpie/resources.py
magpie_cloud-0.1.5.dist-info/licenses/LICENSE
magpie_cloud-0.1.5.dist-info/METADATA
magpie_cloud-0.1.5.dist-info/WHEEL
magpie_cloud-0.1.5.dist-info/top_level.txt
magpie_cloud-0.1.5.dist-info/RECORD
