Metadata-Version: 2.4
Name: magpie-cloud
Version: 0.1.5
Summary: Official Python SDK for Magpie Cloud - Create runtime workers and code sandboxes
Author-email: Magpie Cloud <hello@magpiecloud.com>
License-Expression: MIT
Project-URL: Homepage, https://magpiecloud.com
Project-URL: Documentation, https://api.magpiecloud.com
Project-URL: Repository, https://github.com/yourorg/magpie-cloud
Project-URL: Issues, https://github.com/yourorg/magpie-cloud/issues
Keywords: runtime,cloud,batch,jobs,sandboxes,workers,serverless,code-execution
Classifier: Development Status :: 4 - Beta
Classifier: Intended Audience :: Developers
Classifier: Programming Language :: Python :: 3
Classifier: Programming Language :: Python :: 3.9
Classifier: Programming Language :: Python :: 3.10
Classifier: Programming Language :: Python :: 3.11
Classifier: Programming Language :: Python :: 3.12
Classifier: Topic :: Software Development :: Libraries :: Python Modules
Requires-Python: >=3.9
License-File: LICENSE
Requires-Dist: requests>=2.32.5
Requires-Dist: websocket-client>=1.8.0
Requires-Dist: pydantic>=2.11.9
Provides-Extra: dev
Requires-Dist: pytest>=7.0.0; extra == "dev"
Requires-Dist: pytest-cov>=3.0.0; extra == "dev"
Requires-Dist: black>=22.0.0; extra == "dev"
Requires-Dist: flake8>=4.0.0; extra == "dev"
Dynamic: license-file
